evclust/__init__.py
evclust/bpec.py
evclust/catecm.py
evclust/ccm.py
evclust/datasets/butterfly.csv
evclust/datasets/decathlon.csv
evclust/datasets/edol.csv
evclust/datasets/fourclass.csv
evclust/datasets/iris.csv
evclust/datasets/ProP.mat
evclust/datasets/protein.csv
evclust/datasets.py
evclust/ecm.py
evclust/ecmdd.py
evclust/egmm.py
evclust/kevclus.py
evclust/mecm.py
evclust/mecmdd_rwg.py
evclust/mecmdd_rwl.py
evclust/metrics.py
evclust/recm.py
evclust/utils.py
evclust/wmvec.py
evclust/wmvec_fp.py
evclust-0.2.1.dist-info/LICENSE
evclust-0.2.1.dist-info/METADATA
evclust-0.2.1.dist-info/WHEEL
evclust-0.2.1.dist-info/RECORD
