Metadata-Version: 2.1
Name: evclust
Version: 0.2.1
Summary: Evidential Clustering
License: MIT
Author: Armel SOUBEIGA
Requires-Python: >=3.9,<4.0
Classifier: License :: OSI Approved :: MIT License
Classifier: Programming Language :: Python :: 3
Classifier: Programming Language :: Python :: 3.9
Classifier: Programming Language :: Python :: 3.10
Classifier: Programming Language :: Python :: 3.11
Classifier: Programming Language :: Python :: 3.12
Requires-Dist: matplotlib (>=3.7.1,<4.0.0)
Requires-Dist: myst-parser (>=3.0.1,<4.0.0)
Requires-Dist: pandas (>=2.0.3,<3.0.0)
Requires-Dist: scikit-learn (>=1.3.0,<2.0.0)
Requires-Dist: scipy (>=1.10.0,<2.0.0)
Requires-Dist: seaborn (>=0.12.2,<0.13.0)
Requires-Dist: sphinx-autoapi (>=3.1.2,<4.0.0)
Requires-Dist: sphinx-thebe (>=0.3.1,<0.4.0)
